brailleart/__init__.py
brailleart/__main__.py
brailleart/cli.py
brailleart/converter.py
braille_art-0.0.2.dist-info/LICENSE
braille_art-0.0.2.dist-info/METADATA
braille_art-0.0.2.dist-info/WHEEL
braille_art-0.0.2.dist-info/entry_points.txt
braille_art-0.0.2.dist-info/top_level.txt
braille_art-0.0.2.dist-info/RECORD
