Metadata-Version: 2.1
Name: braille-art
Version: 0.0.2
Summary: Braille art generator
Home-page: https://github.com/feightwywx/braille-art
Author: .direwolf
Author-email: kururinmiracle@outlook.com
License: UNKNOWN
Platform: UNKNOWN
Classifier: Programming Language :: Python :: 3
Classifier: License :: OSI Approved :: MIT License
Classifier: Operating System :: OS Independent
Requires-Python: >=3
License-File: LICENSE
Requires-Dist: numpy (>=1.21.2)
Requires-Dist: opencv-python (>=4.5.3.56)
